pyird/__init__.py
pyird/data/IP_fwhms_h.dat
pyird/data/channel_H.list
pyird/data/channel_YJ.list
pyird/data/hotpix_mask_h_202210_180s.fits
pyird/data/hotpix_mask_y_202210_180s.fits
pyird/data/thar_ird2.dat
pyird/data/thar_mmf2_a_H_20210317.fits
pyird/data/samples/README.md
pyird/data/samples/aprefA
pyird/data/samples/aprefB
pyird/data/samples/aprefC
pyird/data/samples/apref_a
pyird/data/samples/apref_c
pyird/data/samples/wblaze_h_m2_20210317.dat
pyird/data/samples/wflat_m2_20210317.dat
pyird/gp/__init__.py
pyird/gp/gp2d.py
pyird/gp/gputils.py
pyird/image/__init__.py
pyird/image/aptrace.py
pyird/image/bias.py
pyird/image/channel.py
pyird/image/hotpix.py
pyird/image/mask.py
pyird/image/oned_extract.py
pyird/image/operator.py
pyird/image/pattern_model.py
pyird/image/trace_function.py
pyird/io/__init__.py
pyird/io/iraf_trace.py
pyird/io/processRN.py
pyird/io/read_hotpix.py
pyird/io/read_linelist.py
pyird/plot/__init__.py
pyird/plot/detector.py
pyird/plot/order.py
pyird/plot/showmask.py
pyird/plot/showspec.py
pyird/spec/__init__.py
pyird/spec/continuum.py
pyird/spec/normalize.py
pyird/spec/rsdmat.py
pyird/spec/uncertainty.py
pyird/spec/wavcal.py
pyird/utils/__init__.py
pyird/utils/aperture.py
pyird/utils/class_handler.py
pyird/utils/datset.py
pyird/utils/fitsset.py
pyird/utils/fitsutils.py
pyird/utils/getinfo.py
pyird/utils/image_widget.py
pyird/utils/irdstream.py
pyird/utils/large_scaled.py
pyird/utils/maskcheck.py
pyird/utils/remove_fringe.py
pyird-1.1.0.dist-info/LICENSE
pyird-1.1.0.dist-info/METADATA
pyird-1.1.0.dist-info/WHEEL
pyird-1.1.0.dist-info/entry_points.txt
pyird-1.1.0.dist-info/top_level.txt
pyird-1.1.0.dist-info/RECORD
