Metadata-Version: 2.2
Name: pyird
Version: 1.1.0
Summary: Python pipeline for infrared detectors, and/or IRD/REACH
Home-page: https://github.com/prvjapan/pyird
Author: Yui Kasagi, Hajime Kawahara, and Collaborators
Author-email: kasagi.y96@gmail.com
Maintainer: Yui Kasagi, Hajime Kawahara, and Collaborators
Maintainer-email: kasagi.y96@gmail.com
License: MIT
Classifier: Programming Language :: Python
Classifier: Programming Language :: Python :: 3.10
Classifier: Programming Language :: Python :: 3.11
Classifier: Operating System :: OS Independent
Requires-Python: >=3.10
License-File: LICENSE
Requires-Dist: matplotlib
Requires-Dist: tqdm
Requires-Dist: scipy
Requires-Dist: sep
Requires-Dist: gpkron
Requires-Dist: pandas
Requires-Dist: astropy
Requires-Dist: astroquery==0.4.7
Requires-Dist: numpy<2
Provides-Extra: dev
Requires-Dist: pytest; extra == "dev"
Requires-Dist: black; extra == "dev"
